mumu/__init__.py
mumu/config.py
mumu/constant.py
mumu/control.py
mumu/mumu.py
mumu/utils.py
mumu/api/__init__.py
mumu/api/adb/Adb.py
mumu/api/adb/__init__.py
mumu/api/core/Core.py
mumu/api/core/__init__.py
mumu/api/core/app.py
mumu/api/core/performance.py
mumu/api/core/power.py
mumu/api/core/shortcut.py
mumu/api/core/simulation.py
mumu/api/core/window.py
mumu/api/develop/androidevent.py
mumu/api/driver/Driver.py
mumu/api/driver/__init__.py
mumu/api/driver/bridge.py
mumu/api/network/Network.py
mumu/api/network/__init__.py
mumu/api/permission/Permission.py
mumu/api/permission/__init__.py
mumu/api/permission/root.py
mumu/api/screen/__init__.py
mumu/api/screen/gui.py
mumu/api/screen/screen.py
mumu/api/setting/__init__.py
mumu/api/setting/setting.py
mumu_emulator_api-1.0.1.dist-info/LICENSE
mumu_emulator_api-1.0.1.dist-info/METADATA
mumu_emulator_api-1.0.1.dist-info/WHEEL
mumu_emulator_api-1.0.1.dist-info/top_level.txt
mumu_emulator_api-1.0.1.dist-info/RECORD
