Metadata-Version: 2.1
Name: mumu-emulator-api
Version: 1.0.1
Summary: Python API for MuMu Android Emulator
Home-page: https://github.com/wlkjyy/mumu-python-api
Author: wlkjyy
Author-email: wlkjyy@vip.qq.com
Project-URL: Bug Reports, https://github.com/wlkjyy/mumu-python-api/issues
Project-URL: Source, https://github.com/wlkjyy/mumu-python-api
Keywords: mumu emulator android automation api
Classifier: Development Status :: 4 - Beta
Classifier: Intended Audience :: Developers
Classifier: License :: OSI Approved :: MIT License
Classifier: Operating System :: Microsoft :: Windows
Classifier: Programming Language :: Python :: 3
Classifier: Programming Language :: Python :: 3.7
Classifier: Programming Language :: Python :: 3.8
Classifier: Programming Language :: Python :: 3.9
Classifier: Programming Language :: Python :: 3.10
Classifier: Programming Language :: Python :: 3.11
Classifier: Topic :: Software Development :: Libraries :: Python Modules
Classifier: Topic :: System :: Emulators
Requires-Python: >=3.7
License-File: LICENSE
Requires-Dist: opencv-python
Requires-Dist: numpy==1.24.4
Requires-Dist: adbutils==1.2.15
Provides-Extra: gui
Requires-Dist: opencv-python; extra == "gui"
Provides-Extra: scrcpy
Requires-Dist: scrcpy-client; extra == "scrcpy"
